ozon_api_client/__init__.py
ozon_api_client/api/__init__.py
ozon_api_client/api/analytics_api_api.py
ozon_api_client/api/barcode_api_api.py
ozon_api_client/api/beta_method_api.py
ozon_api_client/api/brand_api_api.py
ozon_api_client/api/cancellation_api_api.py
ozon_api_client/api/cargoes_api_api.py
ozon_api_client/api/category_api_api.py
ozon_api_client/api/certification_api_api.py
ozon_api_client/api/chat_api_api.py
ozon_api_client/api/delivery_fbs_api.py
ozon_api_client/api/deliveryr_fbs_api.py
ozon_api_client/api/examples_api.py
ozon_api_client/api/fbo_api.py
ozon_api_client/api/fbo_supply_request_api.py
ozon_api_client/api/fbs_api.py
ozon_api_client/api/fbsr_fbs_marks_api.py
ozon_api_client/api/finance_api_api.py
ozon_api_client/api/pass_api.py
ozon_api_client/api/polygon_api_api.py
ozon_api_client/api/prices_stocks_api_api.py
ozon_api_client/api/pricing_strategy_api_api.py
ozon_api_client/api/product_api_api.py
ozon_api_client/api/promos_api.py
ozon_api_client/api/quants_api.py
ozon_api_client/api/questions_answers_api.py
ozon_api_client/api/report_api_api.py
ozon_api_client/api/return_api_api.py
ozon_api_client/api/returns_api_api.py
ozon_api_client/api/review_api_api.py
ozon_api_client/api/rfbs_returns_api_api.py
ozon_api_client/api/seller_rating_api.py
ozon_api_client/api/supplier_api_api.py
ozon_api_client/api/supply_order_api_api.py
ozon_api_client/api/warehouse_api_api.py
ozon_api_client/api_client.py
ozon_api_client/configuration.py
ozon_api_client/models/__init__.py
ozon_api_client/models/add_strategy_items_response_error.py
ozon_api_client/models/analytics_analytics_get_data_request.py
ozon_api_client/models/analytics_analytics_get_data_response.py
ozon_api_client/models/analytics_data_row.py
ozon_api_client/models/analytics_data_row_dimension.py
ozon_api_client/models/analytics_filter.py
ozon_api_client/models/analytics_get_data_response_result.py
ozon_api_client/models/analytics_get_stock_on_warehouses_request_warehouse_type.py
ozon_api_client-0.1.15.dist-info/METADATA
ozon_api_client-0.1.15.dist-info/WHEEL
ozon_api_client-0.1.15.dist-info/RECORD
