Metadata-Version: 2.1
Name: ozon-api-client
Version: 0.1.15
Summary: 
License: MIT
Author: letby
Author-email: fvahit@gmail.com
Requires-Python: >=3.9,<4.0
Classifier: License :: OSI Approved :: MIT License
Classifier: Programming Language :: Python :: 3
Classifier: Programming Language :: Python :: 3.9
Classifier: Programming Language :: Python :: 3.10
Classifier: Programming Language :: Python :: 3.11
Classifier: Programming Language :: Python :: 3.12
Classifier: Programming Language :: Python :: 3.13
Requires-Dist: certifi (>=2024.2.2,<2025.0.0)
Requires-Dist: python-dateutil (>=2.9.0.post0,<3.0.0)
Requires-Dist: ruamel-yaml (>=0.18.6,<0.19.0)
Requires-Dist: six (==1.10)
Requires-Dist: transliterate (>=1.10.2,<2.0.0)
Requires-Dist: urllib3 (==2.2.1)
